Metadata-Version: 2.1
Name: awscli-plugin-execute-api
Version: 0.2.1
Summary: Plugin to configure a single AWS CLI operation to invoke an API Gateway method
Home-page: https://github.com/nzoschke/awscli-plugin-execute-api
Author: Noah Zoschke
Author-email: noah@mixable.net
License: UNKNOWN
Platform: UNKNOWN
Classifier: Programming Language :: Python :: 3
Classifier: License :: OSI Approved :: Apache Software License
Classifier: Operating System :: OS Independent
